plotcollector/__init__.py
plotcollector/plotcollector.py
plotcollector/data/window.ui
plotcollector-0.1.5.dist-info/LICENSE.txt
plotcollector-0.1.5.dist-info/METADATA
plotcollector-0.1.5.dist-info/WHEEL
plotcollector-0.1.5.dist-info/top_level.txt
plotcollector-0.1.5.dist-info/RECORD
