Metadata-Version: 2.1
Name: plotcollector
Version: 0.1.5
Summary: Matplotlib figure viewer GUI
Home-page: https://github.com/dacts23/plotcollector
Author: David Ávila
Author-email: dacts_23@hotmail.com
License: MIT
Download-URL: https://github.com/dacts23/plotcollector/releases/download/plotcollector-0.1.5/plotcollector-0.1.5-py3-none-any.whl
Keywords: python,plotcollector,matplotlib,GUI
Platform: UNKNOWN
Classifier: Development Status :: 4 - Beta
Classifier: Intended Audience :: Education
Classifier: License :: OSI Approved :: MIT License
Classifier: Programming Language :: Python :: 3
Requires-Dist: PyQt5
Requires-Dist: matplotlib
Requires-Dist: python-pptx
